tracekit/__init__.py
tracekit/client.py
tracekit/snapshot_client.py
tracekit/middleware/__init__.py
tracekit/middleware/django.py
tracekit/middleware/fastapi.py
tracekit/middleware/flask.py
tracekit_apm-1.1.3.dist-info/licenses/LICENSE
tracekit_apm-1.1.3.dist-info/METADATA
tracekit_apm-1.1.3.dist-info/WHEEL
tracekit_apm-1.1.3.dist-info/top_level.txt
tracekit_apm-1.1.3.dist-info/RECORD
