Metadata-Version: 2.4
Name: tracekit-apm
Version: 1.1.3
Summary: TraceKit APM for Python - Zero-config distributed tracing and code monitoring for Flask, FastAPI, and Django
Author-email: TraceKit <support@tracekit.dev>
License: MIT
Project-URL: Homepage, https://tracekit.dev
Project-URL: Documentation, https://app.tracekit.dev/docs/languages/python
Project-URL: Repository, https://github.com/Tracekit-Dev/python-apm
Project-URL: Issues, https://github.com/Tracekit-Dev/python-apm/issues
Keywords: tracekit,apm,tracing,monitoring,opentelemetry,flask,fastapi,django,performance,observability
Classifier: Development Status :: 4 - Beta
Classifier: Intended Audience :: Developers
Classifier: License :: OSI Approved :: MIT License
Classifier: Programming Language :: Python :: 3
Classifier: Programming Language :: Python :: 3.8
Classifier: Programming Language :: Python :: 3.9
Classifier: Programming Language :: Python :: 3.10
Classifier: Programming Language :: Python :: 3.11
Classifier: Programming Language :: Python :: 3.12
Classifier: Topic :: Software Development :: Libraries :: Python Modules
Classifier: Topic :: System :: Monitoring
Requires-Python: >=3.8
License-File: LICENSE
Requires-Dist: opentelemetry-api>=1.20.0
Requires-Dist: opentelemetry-sdk>=1.20.0
Requires-Dist: opentelemetry-exporter-otlp-proto-http>=1.20.0
Requires-Dist: opentelemetry-instrumentation>=0.41b0
Requires-Dist: opentelemetry-instrumentation-requests>=0.41b0
Requires-Dist: opentelemetry-instrumentation-urllib>=0.41b0
Requires-Dist: opentelemetry-instrumentation-urllib3>=0.41b0
Requires-Dist: requests>=2.28.0
Provides-Extra: flask
Requires-Dist: flask>=2.0.0; extra == "flask"
Provides-Extra: fastapi
Requires-Dist: fastapi>=0.100.0; extra == "fastapi"
Requires-Dist: starlette>=0.27.0; extra == "fastapi"
Provides-Extra: django
Requires-Dist: django>=3.2; extra == "django"
Provides-Extra: all
Requires-Dist: flask>=2.0.0; extra == "all"
Requires-Dist: fastapi>=0.100.0; extra == "all"
Requires-Dist: starlette>=0.27.0; extra == "all"
Requires-Dist: django>=3.2; extra == "all"
Dynamic: license-file
